CHANGES.txt
COPYRIGHT.txt
LICENSE.txt
MANIFEST.in
README.txt
bootstrap.py
buildout.cfg
setup.py
src/tranchitella/__init__.py
src/tranchitella.adyen.egg-info/PKG-INFO
src/tranchitella.adyen.egg-info/SOURCES.txt
src/tranchitella.adyen.egg-info/dependency_links.txt
src/tranchitella.adyen.egg-info/namespace_packages.txt
src/tranchitella.adyen.egg-info/not-zip-safe
src/tranchitella.adyen.egg-info/requires.txt
src/tranchitella.adyen.egg-info/top_level.txt
src/tranchitella/adyen/__init__.py
src/tranchitella/adyen/mapping.py