Metadata-Version: 1.0
Name: tranchitella.adyen
Version: 0.3
Summary: Interface to the Adyen payment gateway
Home-page: http://pypi.python.org/pypi/tranchitella.adyen
Author: Tranchitella Kft.
Author-email: info@tranchitella.eu
License: LGPL 2
Platform: UNKNOWN
Classifier: Development Status :: 5 - Production/Stable
Classifier: Intended Audience :: Developers
Classifier: License :: OSI Approved :: GNU Library or Lesser General Public License (LGPL)
Classifier: Operating System :: OS Independent
Classifier: Programming Language :: Python
Classifier: Topic :: Software Development :: Libraries :: Python Modules
